headroom/__init__.py
headroom/cli.py
headroom/client.py
headroom/config.py
headroom/exceptions.py
headroom/parser.py
headroom/py.typed
headroom/tokenizer.py
headroom/utils.py
headroom/backends/__init__.py
headroom/backends/base.py
headroom/backends/litellm.py
headroom/cache/__init__.py
headroom/cache/anthropic.py
headroom/cache/base.py
headroom/cache/compression_feedback.py
headroom/cache/compression_store.py
headroom/cache/dynamic_detector.py
headroom/cache/google.py
headroom/cache/openai.py
headroom/cache/registry.py
headroom/cache/semantic.py
headroom/cache/backends/__init__.py
headroom/cache/backends/base.py
headroom/cache/backends/memory.py
headroom/ccr/__init__.py
headroom/ccr/batch_processor.py
headroom/ccr/batch_store.py
headroom/ccr/context_tracker.py
headroom/ccr/mcp_server.py
headroom/ccr/response_handler.py
headroom/ccr/tool_injection.py
headroom/cli/__init__.py
headroom/cli/__main__.py
headroom/cli/evals.py
headroom/cli/main.py
headroom/cli/memory.py
headroom/cli/proxy.py
headroom/cli/_utils/__init__.py
headroom/cli/_utils/formatting.py
headroom/cli/_utils/parsers.py
headroom/compression/__init__.py
headroom/compression/detector.py
headroom/compression/masks.py
headroom/compression/universal.py
headroom/compression/handlers/__init__.py
headroom/compression/handlers/base.py
headroom/compression/handlers/code_handler.py
headroom/compression/handlers/json_handler.py
headroom/evals/README.md
headroom/evals/__init__.py
headroom/evals/__main__.py
headroom/evals/batch_compression_eval.py
headroom/evals/core.py
headroom/evals/datasets.py
headroom/evals/metrics.py
headroom/evals/memory/__init__.py
headroom/evals/memory/judge.py
headroom/evals/memory/locomo.py
headroom/evals/memory/runner.py
headroom/evals/memory/runner_v2.py
headroom/evals/memory/runner_v3.py
headroom/evals/reports/__init__.py
headroom/evals/runners/__init__.py
headroom/evals/runners/before_after.py
headroom/image/__init__.py
headroom/image/compressor.py
headroom/image/trained_router.py
headroom_ai-0.3.0.dist-info/METADATA
headroom_ai-0.3.0.dist-info/WHEEL
headroom_ai-0.3.0.dist-info/entry_points.txt
headroom_ai-0.3.0.dist-info/licenses/LICENSE
headroom_ai-0.3.0.dist-info/licenses/NOTICE
headroom_ai-0.3.0.dist-info/RECORD
