Metadata-Version: 2.4
Name: headroom-ai
Version: 0.3.0
Summary: The Context Optimization Layer for LLM Applications - Cut costs by 50-90%
Project-URL: Homepage, https://github.com/chopratejas/headroom
Project-URL: Documentation, https://github.com/chopratejas/headroom#readme
Project-URL: Repository, https://github.com/chopratejas/headroom
Project-URL: Issues, https://github.com/chopratejas/headroom/issues
Project-URL: Changelog, https://github.com/chopratejas/headroom/blob/main/CHANGELOG.md
Author: Headroom Contributors
Maintainer: Headroom Contributors
License-Expression: Apache-2.0
License-File: LICENSE
License-File: NOTICE
Keywords: ai,anthropic,caching,claude,compression,context,gpt,llm,machine-learning,openai,optimization,proxy,token
Classifier: Development Status :: 4 - Beta
Classifier: Intended Audience :: Developers
Classifier: License :: OSI Approved :: Apache Software License
Classifier: Operating System :: OS Independent
Classifier: Programming Language :: Python :: 3
Classifier: Programming Language :: Python :: 3.10
Classifier: Programming Language :: Python :: 3.11
Classifier: Programming Language :: Python :: 3.12
Classifier: Topic :: Scientific/Engineering :: Artificial Intelligence
Classifier: Topic :: Software Development :: Libraries :: Python Modules
Classifier: Typing :: Typed
Requires-Python: >=3.10
Requires-Dist: accelerate>=1.12.0
Requires-Dist: click>=8.1.0
Requires-Dist: datasets>=4.5.0
Requires-Dist: hnswlib>=0.8.0
Requires-Dist: litellm>=1.0.0
Requires-Dist: openai>=2.14.0
Requires-Dist: pillow>=10.0.0
Requires-Dist: protobuf>=6.33.4
Requires-Dist: pydantic>=2.0.0
Requires-Dist: rich>=13.0.0
Requires-Dist: semantic-router>=0.1.12
Requires-Dist: sentence-transformers>=5.2.0
Requires-Dist: sentencepiece>=0.2.1
Requires-Dist: tiktoken>=0.5.0
Provides-Extra: agno
Requires-Dist: agno>=1.0.0; extra == 'agno'
Provides-Extra: all
Requires-Dist: anthropic>=0.18.0; extra == 'all'
Requires-Dist: datasets>=2.14.0; extra == 'all'
Requires-Dist: fastapi>=0.100.0; extra == 'all'
Requires-Dist: hnswlib>=0.8.0; extra == 'all'
Requires-Dist: httpx[http2]>=0.24.0; extra == 'all'
Requires-Dist: jinja2>=3.0.0; extra == 'all'
Requires-Dist: llmlingua>=0.2.0; extra == 'all'
Requires-Dist: numpy>=1.24.0; extra == 'all'
Requires-Dist: onnxruntime>=1.16.0; extra == 'all'
Requires-Dist: openai>=1.0.0; extra == 'all'
Requires-Dist: scikit-learn>=1.3.0; extra == 'all'
Requires-Dist: sentence-transformers>=2.2.0; extra == 'all'
Requires-Dist: torch>=2.0.0; extra == 'all'
Requires-Dist: transformers>=4.30.0; extra == 'all'
Requires-Dist: tree-sitter-language-pack>=0.10.0; extra == 'all'
Requires-Dist: uvicorn>=0.23.0; extra == 'all'
Provides-Extra: bedrock
Requires-Dist: boto3>=1.28.0; extra == 'bedrock'
Provides-Extra: code
Requires-Dist: tree-sitter-language-pack>=0.10.0; extra == 'code'
Provides-Extra: dev
Requires-Dist: anthropic>=0.18.0; extra == 'dev'
Requires-Dist: hnswlib>=0.8.0; extra == 'dev'
Requires-Dist: langchain-ollama>=0.2.0; extra == 'dev'
Requires-Dist: mypy>=1.0.0; extra == 'dev'
Requires-Dist: ollama>=0.4.0; extra == 'dev'
Requires-Dist: openai>=1.0.0; extra == 'dev'
Requires-Dist: pre-commit>=3.0.0; extra == 'dev'
Requires-Dist: pytest-asyncio>=0.21.0; extra == 'dev'
Requires-Dist: pytest-cov>=4.0.0; extra == 'dev'
Requires-Dist: pytest>=7.0.0; extra == 'dev'
Requires-Dist: ruff>=0.1.0; extra == 'dev'
Provides-Extra: evals
Requires-Dist: anthropic>=0.18.0; extra == 'evals'
Requires-Dist: datasets>=2.14.0; extra == 'evals'
Requires-Dist: numpy>=1.24.0; extra == 'evals'
Requires-Dist: openai>=1.0.0; extra == 'evals'
Requires-Dist: scikit-learn>=1.3.0; extra == 'evals'
Requires-Dist: sentence-transformers>=2.2.0; extra == 'evals'
Provides-Extra: llmlingua
Requires-Dist: llmlingua>=0.2.0; extra == 'llmlingua'
Requires-Dist: torch>=2.0.0; extra == 'llmlingua'
Requires-Dist: transformers>=4.30.0; extra == 'llmlingua'
Provides-Extra: memory
Requires-Dist: hnswlib>=0.8.0; extra == 'memory'
Provides-Extra: proxy
Requires-Dist: fastapi>=0.100.0; extra == 'proxy'
Requires-Dist: httpx[http2]>=0.24.0; extra == 'proxy'
Requires-Dist: uvicorn>=0.23.0; extra == 'proxy'
Provides-Extra: relevance
Requires-Dist: numpy>=1.24.0; extra == 'relevance'
Requires-Dist: sentence-transformers>=2.2.0; extra == 'relevance'
Provides-Extra: reports
Requires-Dist: jinja2>=3.0.0; extra == 'reports'
Provides-Extra: voice
Requires-Dist: onnxruntime>=1.16.0; extra == 'voice'
Requires-Dist: torch>=2.0.0; extra == 'voice'
Requires-Dist: transformers>=4.30.0; extra == 'voice'
Provides-Extra: voice-train
Requires-Dist: accelerate>=0.20.0; extra == 'voice-train'
Requires-Dist: datasets>=2.14.0; extra == 'voice-train'
Requires-Dist: onnxruntime>=1.16.0; extra == 'voice-train'
Requires-Dist: torch>=2.0.0; extra == 'voice-train'
Requires-Dist: transformers>=4.30.0; extra == 'voice-train'
